flask_nav/__init__.py
flask_nav/elements.py
flask_nav/renderers.py
flask_nav_current-0.0.7.dist-info/LICENSE
flask_nav_current-0.0.7.dist-info/METADATA
flask_nav_current-0.0.7.dist-info/WHEEL
flask_nav_current-0.0.7.dist-info/top_level.txt
flask_nav_current-0.0.7.dist-info/RECORD
