Metadata-Version: 2.1
Name: flask-nav-current
Version: 0.0.7
Summary: Easily create navigation for Flask applications.
Home-page: http://github.com/mbr/flask-nav
Author: Marc Brinkmann
Author-email: git@marcbrinkmann.de
License: MIT
Classifier: Programming Language :: Python :: 3.11
License-File: LICENSE
Requires-Dist: flask
Requires-Dist: visitor
Requires-Dist: dominate
